ranked/__init__.py
ranked/calibration.py
ranked/matchmaker.py
ranked/simulation.py
ranked/datasets/__init__.py
ranked/datasets/dota2.py
ranked/datasets/replay.py
ranked/datasets/synthetic.py
ranked/models/__init__.py
ranked/models/elo.py
ranked/models/elochess.py
ranked/models/glicko2.py
ranked/models/noskill.py
ranked/models/openskill.py
ranked/utils/__init__.py
ranked-1.0.2.dist-info/LICENSE
ranked-1.0.2.dist-info/METADATA
ranked-1.0.2.dist-info/WHEEL
ranked-1.0.2.dist-info/top_level.txt
ranked-1.0.2.dist-info/zip-safe
ranked-1.0.2.dist-info/RECORD
