Metadata-Version: 2.1
Name: ranked
Version: 1.0.2
Summary: Player Ranking Algorithm benchmarks
Home-page: https://github.com/Delaunay/ranked
Author: Pierre Delaunay
Author-email: pierre@delaunay.io
License: BSD-3-Clause
Classifier: Development Status :: 1 - Planning
Classifier: Intended Audience :: Developers
Classifier: Intended Audience :: Education
Classifier: Intended Audience :: Science/Research
Classifier: License :: OSI Approved :: BSD License
Classifier: Operating System :: POSIX
Classifier: Operating System :: Unix
Classifier: Programming Language :: Python
Classifier: Topic :: Scientific/Engineering
Classifier: Topic :: Scientific/Engineering :: Artificial Intelligence
Classifier: Programming Language :: Python :: 3
Classifier: Programming Language :: Python :: 3.8
Classifier: Programming Language :: Python :: 3.9
Classifier: Programming Language :: Python :: 3.10
Classifier: Programming Language :: Python :: 3.11
Requires-Python: >=3.7
License-File: LICENSE
Requires-Dist: scipy
Requires-Dist: altair
Requires-Dist: trueskill
Requires-Dist: openskill
Requires-Dist: numpy
Requires-Dist: orion
Requires-Dist: typing-extensions
